Workbook
Name Slicer_Category: #N/A
Name Slicer_Category_Clean: #N/A
Name Slicer_Expiry_Risk_Level: #N/A
Name Slicer_Supplier_Name_Clean: #N/A
Name Slicer_Table1_Expiry_Risk_Level: #N/A
Name Slicer_Warehouse_Location: #N/A

Sheet Raw_Data
A1: Product_ID | B1: Product_Name | C1: Catagory | D1: Supplier_ID | E1: Supplier_Name | F1: Stock_Quantity | G1: Reorder_Level | H1: Reorder_Quantity | I1: Unit_Price | J1: Date_Received | K1: Last_Order_Date | L1: Expiration_Date | M1: Warehouse_Location | N1: Sales_Volume | O1: Inventory_Turnover_Rate | P1: Status
A2: 29-205-1132 | B2: Sushi Rice | C2: Grains & Pulses | D2: 38-037-1699 | E2: Jaxnation | F2: 22 | G2: 72 | H2: 70 | I2: $4.50 | J2: 8/16/2024 | K2: 6/29/2024 | L2: 46354 | M2: 48 Del Sol Trail | N2: 32 | O2: 19 | P2: Discontinued
A3: 40-681-9981 | B3: Arabica Coffee | C3: Beverages | D3: 54-470-2479 | E3: Feedmix | F3: 45 | G3: 77 | H3: 2 | I3: $20.00 | J3: 45302 | K3: 5/29/2024 | L3: 45664 | M3: 36 3rd Place | N3: 85 | O3: 1 | P3: Discontinued
A4: 06-955-3428 | B4: Black Rice | C4: Grains & Pulses | D4: 54-031-2945 | E4: Vinder | F4: 30 | G4: 38 | H4: 83 | I4: $6.00 | J4: 45359 | K4: 45571 | L4: 46674 | M4: 3296 Walton Court | N4: 31 | O4: 34 | P4: Backordered
A5: 71-594-6552 | B5: Long Grain Rice | C5: Grains & Pulses | D5: 63-492-7603 | E5: Brightbean | F5: 12 | G5: 59 | H5: 62 | I5: $1.50 | J5: 45516 | K5: 2/19/2025 | L5: 45731 | M5: 3 Westerfield Crossing | N5: 95 | O5: 99 | P5: Active
A6: 57-437-1828 | B6: Plum | C6: Fruits & Vegetables | D6: 54-226-4308 | E6: Topicstorm | F6: 37 | G6: 30 | H6: 74 | I6: $4.00 | J6: 45358 | K6: 45606 | L6: 46144 | M6: 15068 Scoville Court | N6: 62 | O6: 25 | P6: Backordered
A7: 21-120-6238 | B7: All-Purpose Flour | C7: Grains & Pulses | D7: 86-292-4587 | E7: Dabjam | F7: 55 | G7: 33 | H7: 14 | I7: $1.75 | J7: 45363 | K7: 5/26/2024 | L7: 46714 | M7: 050 Mcbride Avenue | N7: 34 | O7: 62 | P7: Discontinued
A8: 71-516-1996 | B8: Corn Oil | C8: Oils & Fats | D8: 04-391-7610 | E8: Tagfeed | F8: 96 | G8: 52 | H8: 16 | I8: $2.50 | J8: 3/18/2024 | K8: 45478 | L8: 46599 | M8: 12 Truax Court | N8: 67 | O8: 13 | P8: Active
A9: 39-629-5554 | B9: Egg (Goose) | C9: Dairy | D9: 67-679-4930 | E9: Muxo | F9: 44 | G9: 90 | H9: 17 | I9: $2.50 | J9: 45718 | K9: 45539 | L9: 46068 | M9: 267 International Plaza | N9: 21 | O9: 91 | P9: Discontinued
A10: 66-268-8345 | B10: Greek Yogurt | C10: Dairy | D10: 32-182-1895 | E10: Thoughtstorm | F10: 91 | G10: 84 | H10: 11 | I10: $3.00 | J10: 45394 | K10: 45328 | L10: 46602 | M10: 550 Clemons Plaza | N10: 56 | O10: 90 | P10: Active
A11: 46-452-9419 | B11: Egg (Duck) | C11: Dairy | D11: 67-137-4215 | E11: Wordify | F11: 43 | G11: 10 | H11: 15 | I11: $1.00 | J11: 11/18/2024 | K11: 11/14/2024 | L11: 45913 | M11: 55782 Welch Hill | N11: 27 | O11: 69 | P11: Active
A12: 51-469-4611 | B12: Long Grain Rice | C12: Grains & Pulses | D12: 62-029-0827 | E12: Fivebridge | F12: 62 | G12: 81 | H12: 91 | I12: $1.60 | J12: 12/18/2024 | K12: 5/24/2024 | L12: 46854 | M12: 04776 Saint Paul Park | N12: 100 | O12: 42 | P12: Discontinued
A13: 42-220-9305 | B13: White Sugar | C13: Grains & Pulses | D13: 56-092-7992 | E13: Zooxo | F13: 91 | G13: 98 | H13: 6 | I13: $2.00 | J13: 10/19/2024 | K13: 45608 | L13: 46610 | M13: 61932 Cascade Crossing | N13: 100 | O13: 20 | P13: Backordered
A14: 75-094-1179 | B14: Rye Bread | C14: Bakery | D14: 57-615-0729 | E14: Vitz | F14: 26 | G14: 79 | H14: 31 | I14: $3.00 | J14: 12/13/2024 | K14: 45902 | L14: 46218 | M14: 13 Forest Run Place | N14: 47 | O14: 41 | P14: Discontinued
A15: 11-073-0189 | B15: Plum | C15: Fruits & Vegetables | D15: 75-190-3627 | E15: Voomm | F15: 95 | G15: 50 | H15: 76 | I15: $4.00 | J15: 45416 | K15: 9/21/2024 | L15: 45790 | M15: 5104 Jana Court | N15: 69 | O15: 5 | P15: Active
A16: 22-621-2774 | B16: Strawberries | C16: Fruits & Vegetables | D16: 70-901-6191 | E16: Babblestorm | F16: 54 | G16: 26 | H16: 16 | I16: $6.00 | J16: 45599 | K16: 6/30/2024 | L16: 45873 | M16: 00 Drewry Court | N16: 63 | O16: 97 | P16: Active
A17: 39-449-0772 | B17: Feta Cheese | C17: Dairy | D17: 84-504-7617 | E17: Youfeed | F17: 94 | G17: 13 | H17: 15 | I17: $7.00 | J17: 2/27/2024 | K17: 45326 | L17: 46145 | M17: 195 Portage Junction | N17: 20 | O17: 24 | P17: Backordered
A18: 55-936-2406 | B18: Bread Flour | C18: Grains & Pulses | D18: 29-689-5014 | E18: Mynte | F18: 27 | G18: 93 | H18: 88 | I18: $1.50 | J18: 11/16/2024 | K18: 45538 | L18: 46236 | M18: 52691 8th Drive | N18: 66 | O18: 13 | P18: Active
A19: 82-041-7211 | B19: Swiss Cheese | C19: Dairy | D19: 03-615-0558 | E19: Reallinks | F19: 49 | G19: 49 | H19: 26 | I19: $8.00 | J19: 45574 | K19: 5/19/2024 | L19: 46314 | M19: 285 1st Park | N19: 78 | O19: 61 | P19: Discontinued
A20: 48-414-6162 | B20: Arabica Coffee | C20: Beverages | D20: 10-060-8515 | E20: Skivee | F20: 55 | G20: 93 | H20: 84 | I20: $20.00 | J20: 5/29/2024 | K20: 45515 | L20: 46380 | M20: 17780 Lindbergh Junction | N20: 46 | O20: 84 | P20: Active
A21: 76-854-0095 | B21: White Sugar | C21: Grains & Pulses | D21: 38-883-3382 | E21: Mydeo | F21: 65 | G21: 61 | H21: 82 | I21: $2.00 | J21: 5/31/2024 | K21: 45871 | L21: 45989 | M21: 7834 Cordelia Alley | N21: 29 | O21: 11 | P21: Backordered
A22: 25-349-7974 | B22: Spinach | C22: Fruits & Vegetables | D22: 82-737-6019 | E22: Devshare | F22: 72 | G22: 70 | H22: 99 | I22: $2.50 | J22: 45483 | K22: 5/28/2024 | L22: 46047 | M22: 42 Bunker Hill Junction | N22: 82 | O22: 32 | P22: Discontinued
A23: 66-627-9752 | B23: Trout | C23: Seafood | D23: 87-839-6400 | E23: Jabbertype | F23: 49 | G23: 73 | H23: 48 | I23: $12.00 | J23: 8/17/2024 | K23: 45301 | L23: 45749 | M23: 08 Randy Junction | N23: 52 | O23: 62 | P23: Active
A24: 78-614-4402 | B24: Green Beans | C24: Fruits & Vegetables | D24: 51-014-4287 | E24: Gigazoom | F24: 81 | G24: 99 | H24: 28 | I24: $2.00 | J24: 9/30/2024 | K24: 2/14/2025 | L24: 46139 | M24: 37 Browning Trail | N24: 20 | O24: 85 | P24: Discontinued
A25: 67-025-1245 | B25: Cabbage | C25: Fruits & Vegetables | D25: 28-575-0716 | E25: Chatterbridge | F25: 88 | G25: 46 | H25: 55 | I25: $1.00 | J25: 45539 | K25: 45446 | L25: 46320 | M25: 51890 Lindbergh Terrace | N25: 73 | O25: 63 | P25: Active
A26: 68-418-6724 | B26: Parmesan Cheese | C26: Dairy | D26: 75-465-6257 | E26: Feedspan | F26: 63 | G26: 4 | H26: 85 | I26: $12.00 | J26: 12/21/2024 | K26: 1/13/2025 | L26: 45969 | M26: 49869 Bunker Hill Terrace | N26: 59 | O26: 71 | P26: Active
A27: 40-795-0753 | B27: Raw Sugar | C27: Grains & Pulses | D27: 47-183-4911 | E27: Mydo | F27: 31 | G27: 43 | H27: 80 | I27: $1.50 | J27: 5/28/2024 | K27: 2/22/2025 | L27: 46388 | M27: 66879 Susan Place | N27: 46 | O27: 78 | P27: Backordered
A28: 02-508-3777 | B28: Egg (Quail) | C28: Dairy | D28: 69-933-2582 | E28: Realpoint | F28: 97 | G28: 88 | H28: 81 | I28: $0.80 | J28: 45423 | K28: 45480 | L28: 46440 | M28: 895 Northland Hill | N28: 97 | O28: 18 | P28: Discontinued
A29: 79-741-0770 | B29: Mushrooms | C29: Fruits & Vegetables | D29: 67-771-7656 | E29: Photospace | F29: 72 | G29: 87 | H29: 39 | I29: $6.00 | J29: 6/24/2024 | K29: 2/24/2025 | L29: 46381 | M29: 91 Kinsman Terrace | N29: 94 | O29: 57 | P29: Active
A30: 31-211-5803 | B30: Oatmeal Biscuit | C30: Bakery | D30: 75-503-9347 | E30: Gigazoom | F30: 16 | G30: 9 | H30: 32 | I30: $5.00 | J30: 7/16/2024 | K30: 8/21/2024 | L30: 45851 | M30: 492 Shoshone Road | N30: 50 | O30: 98 | P30: Backordered
A31: 16-499-5059 | B31: Pear | C31: Fruits & Vegetables | D31: 09-090-6360 | E31: Centizu | F31: 77 | G31: 20 | H31: 5 | I31: $4.50 | J31: 8/18/2024 | K31: 11/19/2024 | L31: 46131 | M31: 3 Hooker Way | N31: 61 | O31: 62 | P31: Discontinued
A32: 76-340-4432 | B32: Cucumber | C32: Fruits & Vegetables | D32: 79-915-4185 | E32: Brainverse | F32: 19 | G32: 36 | H32: 72 | I32: $1.75 | J32: 45356 | K32: 3/28/2024 | L32: 46478 | M32: 157 David Center | N32: 31 | O32: 81 | P32: Backordered
A33: 38-732-7667 | B33: Pineapple | C33: Fruits & Vegetables | D33: 88-663-3393 | E33: Photojam | F33: 18 | G33: 52 | H33: 22 | I33: $3.50 | J33: 8/23/2024 | K33: 10/13/2024 | L33: 45894 | M33: 3645 Ridge Oak Drive | N33: 42 | O33: 32 | P33: Backordered
A34: 04-240-2226 | B34: Olive Oil | C34: Oils & Fats | D34: 65-842-6819 | E34: Kamba | F34: 47 | G34: 48 | H34: 73 | I34: $6.00 | J34: 8/13/2024 | K34: 6/28/2024 | L34: 46511 | M34: 504 Green Park | N34: 42 | O34: 51 | P34: Discontinued
A35: 79-136-9840 | B35: Herbal Tea | C35: Beverages | D35: 07-809-0926 | E35: Pixonyx | F35: 77 | G35: 45 | H35: 75 | I35: $30.00 | J35: 45423 | K35: 8/19/2024 | L35: 46543 | M35: 26175 Oxford Way | N35: 25 | O35: 37 | P35: Discontinued
A36: 73-401-5721 | B36: Haddock | C36: Seafood | D36: 38-622-5251 | E36: Midel | F36: 46 | G36: 28 | H36: 73 | I36: $9.00 | J36: 5/28/2024 | K36: 10/28/2024 | L36: 46055 | M36: 582 Sauthoff Crossing | N36: 65 | O36: 57 | P36: Discontinued
A37: 91-848-0606 | B37: Onion | C37: Fruits & Vegetables | D37: 68-836-0350 | E37: Skyble | F37: 39 | G37: 22 | H37: 73 | I37: $2.00 | J37: 45602 | K37: 7/23/2024 | L37: 46711 | M37: 13 Corscot Hill | N37: 60 | O37: 2 | P37: Active
A38: 54-109-8062 | B38: Sushi Rice | C38: Grains & Pulses | D38: 04-726-3363 | E38: Linklinks | F38: 75 | G38: 69 | H38: 100 | I38: $4.50 | J38: 45603 | K38: 1/19/2025 | L38: 45996 | M38: 67 Little Fleur Road | N38: 43 | O38: 18 | P38: Backordered
A39: 70-612-2531 | B39: Pineapple | C39: Fruits & Vegetables | D39: 94-217-4781 | E39: Flipbug | F39: 48 | G39: 48 | H39: 39 | I39: $3.45 | J39: 3/17/2024 | K39: 1/25/2025 | L39: 45823 | M39: 4 Raven Drive | N39: 51 | O39: 50 | P39: Discontinued
A40: 26-161-6692 | B40: Zucchini | C40: Fruits & Vegetables | D40: 61-796-7912 | E40: Kare | F40: 61 | G40: 90 | H40: 26 | I40: $2.50 | J40: 12/22/2024 | K40: 45482 | L40: 46575 | M40: 70001 Vahlen Lane | N40: 79 | O40: 84 | P40: Discontinued
A41: 43-893-5408 | B41: Short Grain Rice | C41: Grains & Pulses | D41: 25-414-2945 | E41: Snaptags | F41: 60 | G41: 90 | H41: 85 | I41: $3.00 | J41: 1/21/2025 | K41: 3/20/2024 | L41: 45955 | M41: 6 Orin Place | N41: 47 | O41: 9 | P41: Discontinued
A42: 11-316-8405 | B42: Mango | C42: Fruits & Vegetables | D42: 50-918-1373 | E42: Twitternation | F42: 24 | G42: 55 | H42: 51 | I42: $5.00 | J42: 4/26/2024 | K42: 2/24/2025 | L42: 46131 | M42: 108 Morning Center | N42: 39 | O42: 15 | P42: Discontinued
A43: 34-086-3222 | B43: Lemon | C43: Fruits & Vegetables | D43: 34-017-9457 | E43: Layo | F43: 12 | G43: 7 | H43: 48 | I43: $2.30 | J43: 6/24/2024 | K43: 12/25/2024 | L43: 46016 | M43: 867 Merrick Place | N43: 66 | O43: 4 | P43: Discontinued
A44: 21-816-1004 | B44: Black Coffee | C44: Beverages | D44: 68-482-4786 | E44: Realpoint | F44: 84 | G44: 13 | H44: 88 | I44: $15.00 | J44: 1/26/2025 | K44: 45394 | L44: 46243 | M44: 564 Hazelcrest Crossing | N44: 25 | O44: 34 | P44: Backordered
A45: 43-693-2092 | B45: Butter | C45: Dairy | D45: 19-469-9841 | E45: Kayveo | F45: 51 | G45: 100 | H45: 70 | I45: $3.00 | J45: 4/30/2024 | K45: 10/21/2024 | L45: 46608 | M45: 76 Toban Plaza | N45: 40 | O45: 21 | P45: Discontinued
A46: 63-270-7076 | B46: Multigrain Bread | C46: Bakery | D46: 85-532-0172 | E46: Roombo | F46: 65 | G46: 36 | H46: 37 | I46: $3.50 | J46: 4/21/2024 | K46: 45632 | L46: 46483 | M46: 6 Lunder Parkway | N46: 32 | O46: 70 | P46: Backordered
A47: 90-230-9767 | B47: Long Grain Rice | C47: Grains & Pulses | D47: 70-515-9048 | E47: Voonyx | F47: 67 | G47: 88 | H47: 32 | I47: $1.50 | J47: 45447 | K47: 45296 | L47: 46536 | M47: 00397 Bay Terrace | N47: 66 | O47: 42 | P47: Discontinued
A48: 05-334-2923 | B48: Bread Flour | C48: Grains & Pulses | D48: 41-772-6271 | E48: Browsezoom | F48: 14 | G48: 74 | H48: 71 | I48: $1.50 | J48: 8/18/2024 | K48: 11/22/2024 | L48: 45911 | M48: 8 Surrey Pass | N48: 37 | O48: 22 | P48: Discontinued
A49: 52-481-5224 | B49: Kiwi | C49: Fruits & Vegetables | D49: 46-382-2024 | E49: Fiveclub | F49: 45 | G49: 24 | H49: 61 | I49: $6.00 | J49: 1/21/2025 | K49: 45840 | L49: 46394 | M49: 80 Old Shore Plaza | N49: 44 | O49: 34 | P49: Backordered
A50: 11-325-7396 | B50: Mango | C50: Fruits & Vegetables | D50: 98-940-7545 | E50: Skipfire | F50: 92 | G50: 46 | H50: 13 | I50: $5.00 | J50: 7/28/2024 | K50: 10/18/2024 | L50: 46086 | M50: 387 Jay Point | N50: 24 | O50: 75 | P50: Discontinued
A51: 70-854-6891 | B51: Sourdough Bread | C51: Bakery | D51: 79-575-9351 | E51: Flashspan | F51: 41 | G51: 84 | H51: 90 | I51: $4.00 | J51: 1/28/2025 | K51: 11/28/2024 | L51: 46177 | M51: 24045 Bluestem Point | N51: 42 | O51: 65 | P51: Active
A52: 46-520-1819 | B52: Short Grain Rice | C52: Grains & Pulses | D52: 10-762-7936 | E52: Katz | F52: 41 | G52: 36 | H52: 78 | I52: $4.50 | J52: 45389 | K52: 45392 | L52: 46428 | M52: 805 Nancy Crossing | N52: 38 | O52: 75 | P52: Backordered
A53: 91-105-7317 | B53: Orange | C53: Fruits & Vegetables | D53: 84-047-0017 | E53: Devshare | F53: 85 | G53: 45 | H53: 71 | I53: $3.00 | J53: 3/20/2024 | K53: 12/28/2024 | L53: 46255 | M53: 44022 Barnett Way | N53: 95 | O53: 72 | P53: Discontinued
A54: 40-751-8635 | B54: Pineapple | C54: Fruits & Vegetables | D54: 48-878-3021 | E54: Yamia | F54: 44 | G54: 80 | H54: 84 | I54: $3.40 | J54: 8/30/2024 | K54: 10/17/2024 | L54: 45766 | M54: 3 Ronald Regan Center | N54: 96 | O54: 68 | P54: Discontinued
A55: 02-920-4829 | B55: White Bread | C55: Bakery | D55: 41-587-4864 | E55: Skyble | F55: 92 | G55: 87 | H55: 84 | I55: $2.50 | J55: 10/19/2024 | K55: 6/14/2024 | L55: 45935 | M55: 4 Judy Hill | N55: 61 | O55: 31 | P55: Backordered
A56: 36-918-2937 | B56: Green Coffee | C56: Beverages | D56: 53-844-0478 | E56: Kwinu | F56: 62 | G56: 89 | H56: 18 | I56: $12.00 | J56: 45629 | K56: 45993 | L56: 45929 | M56: 90865 Sherman Court | N56: 35 | O56: 36 | P56: Active
A57: 68-761-6907 | B57: Zucchini | C57: Fruits & Vegetables | D57: 31-199-3683 | E57: Brainverse | F57: 26 | G57: 18 | H57: 62 | I57: $2.50 | J57: 7/28/2024 | K57: 7/21/2024 | L57: 46828 | M57: 9695 Alpine Trail | N57: 57 | O57: 86 | P57: Discontinued
A58: 69-468-5468 | B58: Sourdough Bread | C58: Bakery | D58: 37-099-6976 | E58: Vinte | F58: 59 | G58: 78 | H58: 6 | I58: $4.50 | J58: 45362 | K58: 45571 | L58: 46368 | M58: 72083 Acker Crossing | N58: 32 | O58: 3 | P58: Active
A59: 27-635-8394 | B59: Orange | C59: Fruits & Vegetables | D59: 87-893-6089 | E59: Twitterwire | F59: 88 | G59: 37 | H59: 61 | I59: $2.90 | J59: 45718 | K59: 11/13/2024 | L59: 46070 | M59: 812 Shelley Circle | N59: 63 | O59: 35 | P59: Discontinued
A60: 41-729-5410 | B60: Sardines | C60: Seafood | D60: 71-727-8611 | E60: Ntag | F60: 91 | G60: 59 | H60: 49 | I60: $6.00 | J60: 10/23/2024 | K60: 45416 | L60: 46374 | M60: 7193 Crownhardt Drive | N60: 30 | O60: 63 | P60: Active
A61: 33-335-9140 | B61: Olive Oil | C61: Oils & Fats | D61: 08-209-1598 | E61: Blogspan | F61: 28 | G61: 17 | H61: 28 | I61: $6.00 | J61: 10/24/2024 | K61: 8/20/2024 | L61: 45748 | M61: 76928 Tennyson Parkway | N61: 38 | O61: 25 | P61: Active
A62: 11-581-9869 | B62: Carrot | C62: Fruits & Vegetables | D62: 22-867-3079 | E62: Avaveo | F62: 51 | G62: 60 | H62: 98 | I62: $1.50 | J62: 45296 | K62: 45638 | L62: 46090 | M62: 44801 Myrtle Center | N62: 44 | O62: 95 | P62: Discontinued
A63: 78-237-0277 | B63: Black Tea | C63: Beverages | D63: 50-314-5433 | E63: Brainbox | F63: 46 | G63: 27 | H63: 76 | I63: $5.00 | J63: 9/15/2024 | K63: 9/23/2024 | L63: 45831 | M63: 79 Cardinal Court | N63: 64 | O63: 96 | P63: Active
A64: 75-152-8731 | B64: Pear | C64: Fruits & Vegetables | D64: 05-593-1927 | E64: Voonix | F64: 82 | G64: 65 | H64: 69 | I64: $4.45 | J64: 45600 | K64: 45637 | L64: 45823 | M64: 622 Anthes Lane | N64: 30 | O64: 78 | P64: Backordered
A65: 65-718-0492 | B65: Olive Oil | C65: Oils & Fats | D65: 91-492-8216 | E65: Midel | F65: 100 | G65: 92 | H65: 26 | I65: $6.00 | J65: 45417 | K65: 1/23/2025 | L65: 46194 | M65: 8626 Chinook Parkway | N65: 84 | O65: 9 | P65: Active
A66: 55-697-5242 | B66: Ricotta Cheese | C66: Dairy | D66: 74-726-0855 | E66: Shufflebeat | F66: 51 | G66: 53 | H66: 88 | I66: $6.00 | J66: 1/31/2025 | K66: 6/30/2024 | L66: 46487 | M66: 19112 Little Fleur Road | N66: 54 | O66: 59 | P66: Discontinued
A67: 14-844-4138 | B67: Black Coffee | C67: Beverages | D67: 90-534-2165 | E67: Flipbug | F67: 61 | G67: 43 | H67: 29 | I67: $15.00 | J67: 45718 | K67: 10/25/2024 | L67: 46269 | M67: 40643 Sullivan Lane | N67: 67 | O67: 6 | P67: Discontinued
A68: 20-225-3930 | B68: White Tea | C68: Beverages | D68: 73-069-2753 | E68: Skipstorm | F68: 99 | G68: 87 | H68: 10 | I68: $25.00 | J68: 45516 | K68: 2/29/2024 | L68: 46218 | M68: 5756 Stephen Avenue | N68: 93 | O68: 70 | P68: Active
A69: 66-993-4234 | B69: Cucumber | C69: Fruits & Vegetables | D69: 15-852-0491 | E69: Gigazoom | F69: 13 | G69: 60 | H69: 100 | I69: $1.80 | J69: 7/18/2024 | K69: 1/16/2025 | L69: 46434 | M69: 22 Dexter Trail | N69: 44 | O69: 32 | P69: Backordered
A70: 87-762-1317 | B70: Mozzarella Cheese | C70: Dairy | D70: 58-474-3510 | E70: Dazzlesphere | F70: 45 | G70: 63 | H70: 75 | I70: $7.00 | J70: 1/28/2025 | K70: 11/20/2024 | L70: 46066 | M70: 9305 Warrior Way | N70: 83 | O70: 5 | P70: Discontinued
A71: 81-844-2979 | B71: Broccoli | C71: Fruits & Vegetables | D71: 02-575-7332 | E71: Realblab | F71: 73 | G71: 87 | H71: 46 | I71: $4.00 | J71: 9/24/2024 | K71: 1/15/2025 | L71: 46163 | M71: 16 Elgar Point | N71: 47 | O71: 67 | P71: Discontinued
A72: 44-408-7594 | B72: Eggplant | C72: Fruits & Vegetables | D72: 08-828-3804 | E72: Eire | F72: 39 | G72: 21 | H72: 5 | I72: $3.00 | J72: 11/24/2024 | K72: 45296 | L72: 46060 | M72: 81 Oneill Circle | N72: 51 | O72: 98 | P72: Backordered
A73: 26-010-9519 | B73: Trout | C73: Seafood | D73: 28-837-4164 | E73: Blogtag | F73: 29 | G73: 72 | H73: 96 | I73: $12.00 | J73: 45356 | K73: 11/26/2024 | L73: 46850 | M73: 4508 Shopko Trail | N73: 85 | O73: 52 | P73: Active
A74: 65-464-5070 | B74: Heavy Cream | C74: Dairy | D74: 01-517-7793 | E74: Ntags | F74: 12 | G74: 60 | H74: 73 | I74: $4.00 | J74: 45718 | K74: 3/16/2024 | L74: 46133 | M74: 00 Luster Alley | N74: 20 | O74: 35 | P74: Discontinued
A75: 07-970-9352 | B75: Bell Pepper | C75: Fruits & Vegetables | D75: 14-724-4622 | E75: Tagtune | F75: 96 | G75: 33 | H75: 72 | I75: $4.45 | J75: 45568 | K75: 5/16/2024 | L75: 46255 | M75: 459 Gateway Pass | N75: 74 | O75: 100 | P75: Active
A76: 88-746-9468 | B76: Onion | C76: Fruits & Vegetables | D76: 06-159-1957 | E76: Skiba | F76: 35 | G76: 92 | H76: 74 | I76: $2.00 | J76: 11/25/2024 | K76: 45718 | L76: 46550 | M76: 82737 Ryan Place | N76: 76 | O76: 32 | P76: Active
A77: 06-336-5482 | B77: Sardines | C77: Seafood | D77: 99-784-4391 | E77: Voolia | F77: 89 | G77: 34 | H77: 15 | I77: $6.00 | J77: 12/31/2024 | K77: 45507 | L77: 45739 | M77: 7 Mockingbird Hill | N77: 60 | O77: 2 | P77: Discontinued
A78: 03-276-3931 | B78: Mango | C78: Fruits & Vegetables | D78: 42-224-8186 | E78: Oyoloo | F78: 60 | G78: 36 | H78: 28 | I78: $4.50 | J78: 6/30/2024 | K78: 9/18/2024 | L78: 46518 | M78: 081 Bellgrove Place | N78: 26 | O78: 29 | P78: Active
A79: 39-232-5341 | B79: Arborio Rice | C79: Grains & Pulses | D79: 23-319-2681 | E79: Feedmix | F79: 20 | G79: 34 | H79: 74 | I79: $4.50 | J79: 9/21/2024 | K79: 10/24/2024 | L79: 46018 | M79: 05433 Towne Terrace | N79: 50 | O79: 83 | P79: Discontinued
A80: 12-239-9399 | B80: Potato | C80: Fruits & Vegetables | D80: 53-584-1853 | E80: Tagtune | F80: 28 | G80: 40 | H80: 27 | I80: $1.20 | J80: 12/14/2024 | K80: 7/29/2024 | L80: 46272 | M80: 924 La Follette Alley | N80: 30 | O80: 56 | P80: Active
A81: 75-080-4909 | B81: Corn Oil | C81: Oils & Fats | D81: 34-726-5887 | E81: Tagopia | F81: 20 | G81: 55 | H81: 15 | I81: $2.50 | J81: 45547 | K81: 45630 | L81: 45871 | M81: 7 Gateway Center | N81: 86 | O81: 61 | P81: Backordered
A82: 70-815-4015 | B82: Butter Biscuit | C82: Bakery | D82: 89-134-9717 | E82: Ozu | F82: 38 | G82: 93 | H82: 61 | I82: $6.00 | J82: 45577 | K82: 7/15/2024 | L82: 46545 | M82: 175 Sycamore Circle | N82: 67 | O82: 100 | P82: Active
A83: 11-032-9778 | B83: Peas | C83: Fruits & Vegetables | D83: 42-380-8881 | E83: Edgepulse | F83: 99 | G83: 1 | H83: 4 | I83: $3.00 | J83: 12/13/2024 | K83: 1/27/2025 | L83: 46192 | M83: 553 Mayfield Crossing | N83: 50 | O83: 53 | P83: Backordered
A84: 54-374-9986 | B84: Cream | C84: Dairy | D84: 33-818-4917 | E84: Oyondu | F84: 92 | G84: 52 | H84: 80 | I84: $2.50 | J84: 45357 | K84: 10/22/2024 | L84: 45976 | M84: 74997 Katie Terrace | N84: 72 | O84: 96 | P84: Discontinued
A85: 77-312-6317 | B85: Spinach | C85: Fruits & Vegetables | D85: 12-950-4397 | E85: Abatz | F85: 41 | G85: 29 | H85: 76 | I85: $2.40 | J85: 2/26/2024 | K85: 9/13/2024 | L85: 45886 | M85: 3616 Carey Pass | N85: 59 | O85: 4 | P85: Discontinued
A86: 13-844-2178 | B86: Sardines | C86: Seafood | D86: 66-832-1802 | E86: Browsetype | F86: 44 | G86: 67 | H86: 48 | I86: $6.00 | J86: 45421 | K86: 9/21/2024 | L86: 45843 | M86: 86207 Tennyson Parkway | N86: 90 | O86: 11 | P86: Active
A87: 22-141-9798 | B87: White Sugar | C87: Grains & Pulses | D87: 59-849-9942 | E87: Photobean | F87: 47 | G87: 7 | H87: 63 | I87: $2.00 | J87: 5/18/2024 | K87: 9/20/2024 | L87: 45917 | M87: 6 Nobel Junction | N87: 29 | O87: 20 | P87: Backordered
A88: 20-022-3173 | B88: Bread Flour | C88: Grains & Pulses | D88: 54-188-1006 | E88: Mydeo | F88: 21 | G88: 63 | H88: 65 | I88: $1.50 | J88: 45514 | K88: 45576 | L88: 46307 | M88: 81878 Nobel Point | N88: 38 | O88: 73 | P88: Discontinued
A89: 26-177-5690 | B89: Cucumber | C89: Fruits & Vegetables | D89: 06-708-1412 | E89: Skinte | F89: 85 | G89: 33 | H89: 50 | I89: $1.80 | J89: 45446 | K89: 7/15/2024 | L89: 46674 | M89: 61707 Mariners Cove Park | N89: 64 | O89: 38 | P89: Discontinued
A90: 70-871-4536 | B90: Swiss Cheese | C90: Dairy | D90: 72-514-7323 | E90: Cogilith | F90: 29 | G90: 4 | H90: 17 | I90: $8.00 | J90: 1/19/2025 | K90: 11/13/2024 | L90: 46220 | M90: 5 Waxwing Junction | N90: 59 | O90: 52 | P90: Active
A91: 06-611-5454 | B91: Peanut Oil | C91: Oils & Fats | D91: 43-786-9229 | E91: Bluezoom | F91: 64 | G91: 21 | H91: 13 | I91: $4.00 | J91: 1/30/2025 | K91: 45606 | L91: 46592 | M91: 16 Autumn Leaf Way | N91: 51 | O91: 26 | P91: Backordered
A92: 89-543-3456 | B92: Blueberries | C92: Fruits & Vegetables | D92: 23-178-8962 | E92: Jaloo | F92: 66 | G92: 40 | H92: 96 | I92: $10.00 | J92: 2/28/2024 | K92: 6/22/2024 | L92: 46560 | M92: 22782 Oriole Way | N92: 24 | O92: 61 | P92: Active
A93: 82-395-5070 | B93: Chocolate Biscuit | C93: Bakery | D93: 01-801-9502 | E93: Vidoo | F93: 75 | G93: 81 | H93: 17 | I93: $5.00 | J93: 45542 | K93: 2/17/2025 | L93: 46028 | M93: 43442 Homewood Street | N93: 69 | O93: 38 | P93: Active
A94: 14-305-5348 | B94: Cheese | C94: Dairy | D94: 71-092-6845 | E94: Shuffledrive | F94: 53 | G94: 63 | H94: 2 | I94: $9.00 | J94: 45330 | K94: 45636 | L94: 46066 | M94: 19 Shoshone Circle | N94: 56 | O94: 95 | P94: Active
A95: 82-243-3180 | B95: Palm Oil | C95: Oils & Fats | D95: 18-631-1458 | E95: Zooxo | F95: 43 | G95: 63 | H95: 80 | I95: $1.80 | J95: 6/23/2024 | K95: 7/31/2024 | L95: 46543 | M95: 97 Sunnyside Court | N95: 33 | O95: 96 | P95: Discontinued
A96: 25-010-9478 | B96: Eggplant | C96: Fruits & Vegetables | D96: 24-576-3402 | E96: Topicblab | F96: 74 | G96: 30 | H96: 24 | I96: $3.00 | J96: 45543 | K96: 10/13/2024 | L96: 45948 | M96: 357 Maple Park | N96: 82 | O96: 12 | P96: Active
A97: 13-202-4809 | B97: Garlic | C97: Fruits & Vegetables | D97: 24-281-7685 | E97: Katz | F97: 27 | G97: 22 | H97: 89 | I97: $7.00 | J97: 45296 | K97: 7/28/2024 | L97: 45853 | M97: 6195 Monterey Center | N97: 91 | O97: 77 | P97: Discontinued
A98: 67-270-7464 | B98: Jasmine Rice | C98: Grains & Pulses | D98: 83-960-5274 | E98: Yadel | F98: 91 | G98: 73 | H98: 77 | I98: $4.75 | J98: 45659 | K98: 8/24/2024 | L98: 46570 | M98: 7242 Claremont Avenue | N98: 51 | O98: 49 | P98: Discontinued
A99: 11-733-1756 | B99: Rice Flour | C99: Grains & Pulses | D99: 27-970-8649 | E99: Mynte | F99: 52 | G99: 81 | H99: 53 | I99: $2.00 | J99: 8/28/2024 | K99: 11/27/2024 | L99: 46836 | M99: 127 Eliot Road | N99: 95 | O99: 88 | P99: Backordered
A100: 80-988-4653 | B100: Zucchini | C100: Fruits & Vegetables | D100: 02-272-0535 | E100: Livetube | F100: 43 | G100: 66 | H100: 85 | I100: $2.50 | J100: 4/20/2024 | K100: 9/14/2024 | L100: 46053 | M100: 8 Russell Pass | N100: 66 | O100: 65 | P100: Discontinued
...

Sheet Clean_Data
A1: Product_ID | B1: Product_Name | C1: Product_Name_Clean | D1: Category | E1: Category_Clean | F1: Supplier_ID | G1: Supplier_Name | H1: Supplier_Name_Clean | I1: Stock_Quantity | J1: Reorder_Level | K1: Reorder_Quantity | L1: Stock_Status | M1: Unit_Price | N1: Unit_Price_Clean | O1: Date_Received | P1: Last_Order_Date | Q1: Expiration_Date | R1: Expiry_Risk | S1: Warehouse_Location | T1: Sales_Volume | U1: Inventory_Value | V1: Status | W1: Total_Inventory_Value | X1: Estimated_Sales_Revenue | Y1: Turnover_Status | Z1: Days_To_Expiry | AA1: Expiry_Risk_Level | AB1: Stock_Risk_Level | AC1: Reorder_Cost_Estimate | AD1: Product_Health
A2: =Raw_Data!A2 -> 29-205-1132 | B2: Sushi Rice | C2: =TRIM(PROPER(Raw_Data!B2)) -> Sushi Rice | D2: Grains & Pulses | E2: =TRIM(PROPER(Raw_Data!C2)) -> Grains & Pulses | F2: 38-037-1699 | G2: Jaxnation | H2: =TRIM(PROPER(Raw_Data!E2)) -> Jaxnation | I2: 22 | J2: 72 | K2: =MAX(0,(J2*2)-I2) -> 122 | L2: Sufficient Stock | M2: $4.50 | N2: =VALUE(SUBSTITUTE(Raw_Data!I2,"$","")) -> 4.5 | O2: 45520 | P2: 45472 | Q2: =Raw_Data!L2 -> 46354 | R2: =IF(Q2<TODAY(),"Expired", IF(Q2<=TODAY()+30,"High", IF(Q2<=TODAY()+90,"Medium","Low") ) ) -> Low | S2: 48 Del Sol Trail | T2: 32 | U2: =I2 * N2 -> 99 | V2: Discontinued | W2: =I2 * N2 -> 99 | X2: =T2 * N2 -> 144 | Y2: =IF(T2=0,"No Sales", IF(T2/I2>=1,"Fast Moving","Slow Moving")) -> Fast Moving | Z2: =Q2-TODAY() -> 325 | AA2: =IF(Q2<TODAY(),"Expired", IF(Q2-TODAY()<=7,"Critical", IF(Q2-TODAY()<=30,"Expiring Soon","Safe"))) -> Safe | AB2: =IF(I2<J2,"Low Stock","Sufficient") -> Low Stock | AC2: =K2 * N2 -> 549 | AD2: =IF(AND(AA2="Critical",AB2="Low Stock"),"High Risk", IF(AA2="Expired","Loss", IF(AA2="Expiring Soon","Discount Soon", IF(AB2="Low Stock","Reorder Needed","Healthy")))) -> Reorder Needed
A3: =Raw_Data!A3 -> 40-681-9981 | B3: Arabica Coffee | C3: =TRIM(PROPER(Raw_Data!B3)) -> Arabica Coffee | D3: Beverages | E3: =TRIM(PROPER(Raw_Data!C3)) -> Beverages | F3: 54-470-2479 | G3: Feedmix | H3: =TRIM(PROPER(Raw_Data!E3)) -> Feedmix | I3: 45 | J3: 77 | K3: =MAX(0,(J3*2)-I3) -> 109 | L3: Sufficient Stock | M3: $20.00 | N3: =VALUE(SUBSTITUTE(Raw_Data!I3,"$","")) -> 20 | O3: 45302 | P3: 45441 | Q3: =Raw_Data!L3 -> 45664 | R3: =IF(Q3<TODAY(),"Expired", IF(Q3<=TODAY()+30,"High", IF(Q3<=TODAY()+90,"Medium","Low") ) ) -> Expired | S3: 36 3rd Place | T3: 85 | U3: =I3 * N3 -> 900 | V3: Discontinued | W3: =I3 * N3 -> 900 | X3: =T3 * N3 -> 1700 | Y3: =IF(T3=0,"No Sales", IF(T3/I3>=1,"Fast Moving","Slow Moving")) -> Fast Moving | Z3: =Q3-TODAY() -> -365 | AA3: =IF(Q3<TODAY(),"Expired", IF(Q3-TODAY()<=7,"Critical", IF(Q3-TODAY()<=30,"Expiring Soon","Safe"))) -> Expired | AB3: =IF(I3<J3,"Low Stock","Sufficient") -> Low Stock | AC3: =K3 * N3 -> 2180 | AD3: =IF(AND(AA3="Critical",AB3="Low Stock"),"High Risk", IF(AA3="Expired","Loss", IF(AA3="Expiring Soon","Discount Soon", IF(AB3="Low Stock","Reorder Needed","Healthy")))) -> Loss
A4: =Raw_Data!A4 -> 06-955-3428 | B4: Black Rice | C4: =TRIM(PROPER(Raw_Data!B4)) -> Black Rice | D4: Grains & Pulses | E4: =TRIM(PROPER(Raw_Data!C4)) -> Grains & Pulses | F4: 54-031-2945 | G4: Vinder | H4: =TRIM(PROPER(Raw_Data!E4)) -> Vinder | I4: 30 | J4: 38 | K4: =MAX(0,(J4*2)-I4) -> 46 | L4: Reorder Needed | M4: $6.00 | N4: =VALUE(SUBSTITUTE(Raw_Data!I4,"$","")) -> 6 | O4: 45359 | P4: 45571 | Q4: =Raw_Data!L4 -> 46674 | R4: =IF(Q4<TODAY(),"Expired", IF(Q4<=TODAY()+30,"High", IF(Q4<=TODAY()+90,"Medium","Low") ) ) -> Low | S4: 3296 Walton Court | T4: 31 | U4: =I4 * N4 -> 180 | V4: Backordered | W4: =I4 * N4 -> 180 | X4: =T4 * N4 -> 186 | Y4: =IF(T4=0,"No Sales", IF(T4/I4>=1,"Fast Moving","Slow Moving")) -> Fast Moving | Z4: =Q4-TODAY() -> 645 | AA4: =IF(Q4<TODAY(),"Expired", IF(Q4-TODAY()<=7,"Critical", IF(Q4-TODAY()<=30,"Expiring Soon","Safe"))) -> Safe | AB4: =IF(I4<J4,"Low Stock","Sufficient") -> Low Stock | AC4: =K4 * N4 -> 276 | AD4: =IF(AND(AA4="Critical",AB4="Low Stock"),"High Risk", IF(AA4="Expired","Loss", IF(AA4="Expiring Soon","Discount Soon", IF(AB4="Low Stock","Reorder Needed","Healthy")))) -> Reorder Needed
A5: =Raw_Data!A5 -> 71-594-6552 | B5: Long Grain Rice | C5: =TRIM(PROPER(Raw_Data!B5)) -> Long Grain Rice | D5: Grains & Pulses | E5: =TRIM(PROPER(Raw_Data!C5)) -> Grains & Pulses | F5: 63-492-7603 | G5: Brightbean | H5: =TRIM(PROPER(Raw_Data!E5)) -> Brightbean | I5: 12 | J5: 59 | K5: =MAX(0,(J5*2)-I5) -> 106 | L5: Reorder Needed | M5: $1.50 | N5: =VALUE(SUBSTITUTE(Raw_Data!I5,"$","")) -> 1.5 | O5: 45516 | P5: 45707 | Q5: =Raw_Data!L5 -> 45731 | R5: =IF(Q5<TODAY(),"Expired", IF(Q5<=TODAY()+30,"High", IF(Q5<=TODAY()+90,"Medium","Low") ) ) -> Expired | S5: 3 Westerfield Crossing | T5: 95 | U5: =I5 * N5 -> 18 | V5: Active | W5: =I5 * N5 -> 18 | X5: =T5 * N5 -> 142.5 | Y5: =IF(T5=0,"No Sales", IF(T5/I5>=1,"Fast Moving","Slow Moving")) -> Fast Moving | Z5: =Q5-TODAY() -> -298 | AA5: =IF(Q5<TODAY(),"Expired", IF(Q5-TODAY()<=7,"Critical", IF(Q5-TODAY()<=30,"Expiring Soon","Safe"))) -> Expired | AB5: =IF(I5<J5,"Low Stock","Sufficient") -> Low Stock | AC5: =K5 * N5 -> 159 | AD5: =IF(AND(AA5="Critical",AB5="Low Stock"),"High Risk", IF(AA5="Expired","Loss", IF(AA5="Expiring Soon","Discount Soon", IF(AB5="Low Stock","Reorder Needed","Healthy")))) -> Loss
A6: =Raw_Data!A6 -> 57-437-1828 | B6: Plum | C6: =TRIM(PROPER(Raw_Data!B6)) -> Plum | D6: Fruits & Vegetables | E6: =TRIM(PROPER(Raw_Data!C6)) -> Fruits & Vegetables | F6: 54-226-4308 | G6: Topicstorm | H6: =TRIM(PROPER(Raw_Data!E6)) -> Topicstorm | I6: 37 | J6: 30 | K6: =MAX(0,(J6*2)-I6) -> 23 | L6: Reorder Needed | M6: $4.00 | N6: =VALUE(SUBSTITUTE(Raw_Data!I6,"$","")) -> 4 | O6: 45358 | P6: 45606 | Q6: =Raw_Data!L6 -> 46144 | R6: =IF(Q6<TODAY(),"Expired", IF(Q6<=TODAY()+30,"High", IF(Q6<=TODAY()+90,"Medium","Low") ) ) -> Low | S6: 15068 Scoville Court | T6: 62 | U6: =I6 * N6 -> 148 | V6: Backordered | W6: =I6 * N6 -> 148 | X6: =T6 * N6 -> 248 | Y6: =IF(T6=0,"No Sales", IF(T6/I6>=1,"Fast Moving","Slow Moving")) -> Fast Moving | Z6: =Q6-TODAY() -> 115 | AA6: =IF(Q6<TODAY(),"Expired", IF(Q6-TODAY()<=7,"Critical", IF(Q6-TODAY()<=30,"Expiring Soon","Safe"))) -> Safe | AB6: =IF(I6<J6,"Low Stock","Sufficient") -> Sufficient | AC6: =K6 * N6 -> 92 | AD6: =IF(AND(AA6="Critical",AB6="Low Stock"),"High Risk", IF(AA6="Expired","Loss", IF(AA6="Expiring Soon","Discount Soon", IF(AB6="Low Stock","Reorder Needed","Healthy")))) -> Healthy
A7: =Raw_Data!A7 -> 21-120-6238 | B7: All-Purpose Flour | C7: =TRIM(PROPER(Raw_Data!B7)) -> All-Purpose Flour | D7: Grains & Pulses | E7: =TRIM(PROPER(Raw_Data!C7)) -> Grains & Pulses | F7: 86-292-4587 | G7: Dabjam | H7: =TRIM(PROPER(Raw_Data!E7)) -> Dabjam | I7: 55 | J7: 33 | K7: =MAX(0,(J7*2)-I7) -> 11 | L7: Sufficient Stock | M7: $1.75 | N7: =VALUE(SUBSTITUTE(Raw_Data!I7,"$","")) -> 1.75 | O7: 45363 | P7: 45438 | Q7: =Raw_Data!L7 -> 46714 | R7: =IF(Q7<TODAY(),"Expired", IF(Q7<=TODAY()+30,"High", IF(Q7<=TODAY()+90,"Medium","Low") ) ) -> Low | S7: 050 Mcbride Avenue | T7: 34 | U7: =I7 * N7 -> 96.25 | V7: Discontinued | W7: =I7 * N7 -> 96.25 | X7: =T7 * N7 -> 59.5 | Y7: =IF(T7=0,"No Sales", IF(T7/I7>=1,"Fast Moving","Slow Moving")) -> Slow Moving | Z7: =Q7-TODAY() -> 685 | AA7: =IF(Q7<TODAY(),"Expired", IF(Q7-TODAY()<=7,"Critical", IF(Q7-TODAY()<=30,"Expiring Soon","Safe"))) -> Safe | AB7: =IF(I7<J7,"Low Stock","Sufficient") -> Sufficient | AC7: =K7 * N7 -> 19.25 | AD7: =IF(AND(AA7="Critical",AB7="Low Stock"),"High Risk", IF(AA7="Expired","Loss", IF(AA7="Expiring Soon","Discount Soon", IF(AB7="Low Stock","Reorder Needed","Healthy")))) -> Healthy
A8: =Raw_Data!A8 -> 71-516-1996 | B8: Corn Oil | C8: =TRIM(PROPER(Raw_Data!B8)) -> Corn Oil | D8: Oils & Fats | E8: =TRIM(PROPER(Raw_Data!C8)) -> Oils & Fats | F8: 04-391-7610 | G8: Tagfeed | H8: =TRIM(PROPER(Raw_Data!E8)) -> Tagfeed | I8: 96 | J8: 52 | K8: =MAX(0,(J8*2)-I8) -> 8 | L8: Sufficient Stock | M8: $2.50 | N8: =VALUE(SUBSTITUTE(Raw_Data!I8,"$","")) -> 2.5 | O8: 45369 | P8: 45478 | Q8: =Raw_Data!L8 -> 46599 | R8: =IF(Q8<TODAY(),"Expired", IF(Q8<=TODAY()+30,"High", IF(Q8<=TODAY()+90,"Medium","Low") ) ) -> Low | S8: 12 Truax Court | T8: 67 | U8: =I8 * N8 -> 240 | V8: Active | W8: =I8 * N8 -> 240 | X8: =T8 * N8 -> 167.5 | Y8: =IF(T8=0,"No Sales", IF(T8/I8>=1,"Fast Moving","Slow Moving")) -> Slow Moving | Z8: =Q8-TODAY() -> 570 | AA8: =IF(Q8<TODAY(),"Expired", IF(Q8-TODAY()<=7,"Critical", IF(Q8-TODAY()<=30,"Expiring Soon","Safe"))) -> Safe | AB8: =IF(I8<J8,"Low Stock","Sufficient") -> Sufficient | AC8: =K8 * N8 -> 20 | AD8: =IF(AND(AA8="Critical",AB8="Low Stock"),"High Risk", IF(AA8="Expired","Loss", IF(AA8="Expiring Soon","Discount Soon", IF(AB8="Low Stock","Reorder Needed","Healthy")))) -> Healthy
A9: =Raw_Data!A9 -> 39-629-5554 | B9: Egg (Goose) | C9: =TRIM(PROPER(Raw_Data!B9)) -> Egg (Goose) | D9: Dairy | E9: =TRIM(PROPER(Raw_Data!C9)) -> Dairy | F9: 67-679-4930 | G9: Muxo | H9: =TRIM(PROPER(Raw_Data!E9)) -> Muxo | I9: 44 | J9: 90 | K9: =MAX(0,(J9*2)-I9) -> 136 | L9: Sufficient Stock | M9: $2.50 | N9: =VALUE(SUBSTITUTE(Raw_Data!I9,"$","")) -> 2.5 | O9: 45718 | P9: 45539 | Q9: =Raw_Data!L9 -> 46068 | R9: =IF(Q9<TODAY(),"Expired", IF(Q9<=TODAY()+30,"High", IF(Q9<=TODAY()+90,"Medium","Low") ) ) -> Medium | S9: 267 International Plaza | T9: 21 | U9: =I9 * N9 -> 110 | V9: Discontinued | W9: =I9 * N9 -> 110 | X9: =T9 * N9 -> 52.5 | Y9: =IF(T9=0,"No Sales", IF(T9/I9>=1,"Fast Moving","Slow Moving")) -> Slow Moving | Z9: =Q9-TODAY() -> 39 | AA9: =IF(Q9<TODAY(),"Expired", IF(Q9-TODAY()<=7,"Critical", IF(Q9-TODAY()<=30,"Expiring Soon","Safe"))) -> Safe | AB9: =IF(I9<J9,"Low Stock","Sufficient") -> Low Stock | AC9: =K9 * N9 -> 340 | AD9: =IF(AND(AA9="Critical",AB9="Low Stock"),"High Risk", IF(AA9="Expired","Loss", IF(AA9="Expiring Soon","Discount Soon", IF(AB9="Low Stock","Reorder Needed","Healthy")))) -> Reorder Needed
A10: =Raw_Data!A10 -> 66-268-8345 | B10: Greek Yogurt | C10: =TRIM(PROPER(Raw_Data!B10)) -> Greek Yogurt | D10: Dairy | E10: =TRIM(PROPER(Raw_Data!C10)) -> Dairy | F10: 32-182-1895 | G10: Thoughtstorm | H10: =TRIM(PROPER(Raw_Data!E10)) -> Thoughtstorm | I10: 91 | J10: 84 | K10: =MAX(0,(J10*2)-I10) -> 77 | L10: Sufficient Stock | M10: $3.00 | N10: =VALUE(SUBSTITUTE(Raw_Data!I10,"$","")) -> 3 | O10: 45394 | P10: 45328 | Q10: =Raw_Data!L10 -> 46602 | R10: =IF(Q10<TODAY(),"Expired", IF(Q10<=TODAY()+30,"High", IF(Q10<=TODAY()+90,"Medium","Low") ) ) -> Low | S10: 550 Clemons Plaza | T10: 56 | U10: =I10 * N10 -> 273 | V10: Active | W10: =I10 * N10 -> 273 | X10: =T10 * N10 -> 168 | Y10: =IF(T10=0,"No Sales", IF(T10/I10>=1,"Fast Moving","Slow Moving")) -> Slow Moving | Z10: =Q10-TODAY() -> 573 | AA10: =IF(Q10<TODAY(),"Expired", IF(Q10-TODAY()<=7,"Critical", IF(Q10-TODAY()<=30,"Expiring Soon","Safe"))) -> Safe | AB10: =IF(I10<J10,"Low Stock","Sufficient") -> Sufficient | AC10: =K10 * N10 -> 231 | AD10: =IF(AND(AA10="Critical",AB10="Low Stock"),"High Risk", IF(AA10="Expired","Loss", IF(AA10="Expiring Soon","Discount Soon", IF(AB10="Low Stock","Reorder Needed","Healthy")))) -> Healthy
A11: =Raw_Data!A11 -> 46-452-9419 | B11: Egg (Duck) | C11: =TRIM(PROPER(Raw_Data!B11)) -> Egg (Duck) | D11: Dairy | E11: =TRIM(PROPER(Raw_Data!C11)) -> Dairy | F11: 67-137-4215 | G11: Wordify | H11: =TRIM(PROPER(Raw_Data!E11)) -> Wordify | I11: 43 | J11: 10 | K11: =MAX(0,(J11*2)-I11) -> 0 | L11: Reorder Needed | M11: $1.00 | N11: =VALUE(SUBSTITUTE(Raw_Data!I11,"$","")) -> 1 | O11: 45614 | P11: 45610 | Q11: =Raw_Data!L11 -> 45913 | R11: =IF(Q11<TODAY(),"Expired", IF(Q11<=TODAY()+30,"High", IF(Q11<=TODAY()+90,"Medium","Low") ) ) -> Expired | S11: 55782 Welch Hill | T11: 27 | U11: =I11 * N11 -> 43 | V11: Active | W11: =I11 * N11 -> 43 | X11: =T11 * N11 -> 27 | Y11: =IF(T11=0,"No Sales", IF(T11/I11>=1,"Fast Moving","Slow Moving")) -> Slow Moving | Z11: =Q11-TODAY() -> -116 | AA11: =IF(Q11<TODAY(),"Expired", IF(Q11-TODAY()<=7,"Critical", IF(Q11-TODAY()<=30,"Expiring Soon","Safe"))) -> Expired | AB11: =IF(I11<J11,"Low Stock","Sufficient") -> Sufficient | AC11: =K11 * N11 -> 0 | AD11: =IF(AND(AA11="Critical",AB11="Low Stock"),"High Risk", IF(AA11="Expired","Loss", IF(AA11="Expiring Soon","Discount Soon", IF(AB11="Low Stock","Reorder Needed","Healthy")))) -> Loss
A12: =Raw_Data!A12 -> 51-469-4611 | B12: Long Grain Rice | C12: =TRIM(PROPER(Raw_Data!B12)) -> Long Grain Rice | D12: Grains & Pulses | E12: =TRIM(PROPER(Raw_Data!C12)) -> Grains & Pulses | F12: 62-029-0827 | G12: Fivebridge | H12: =TRIM(PROPER(Raw_Data!E12)) -> Fivebridge | I12: 62 | J12: 81 | K12: =MAX(0,(J12*2)-I12) -> 100 | L12: Reorder Needed | M12: $1.60 | N12: =VALUE(SUBSTITUTE(Raw_Data!I12,"$","")) -> 1.6 | O12: 45644 | P12: 45436 | Q12: =Raw_Data!L12 -> 46854 | R12: =IF(Q12<TODAY(),"Expired", IF(Q12<=TODAY()+30,"High", IF(Q12<=TODAY()+90,"Medium","Low") ) ) -> Low | S12: 04776 Saint Paul Park | T12: 100 | U12: =I12 * N12 -> 99.2 | V12: Discontinued | W12: =I12 * N12 -> 99.2 | X12: =T12 * N12 -> 160 | Y12: =IF(T12=0,"No Sales", IF(T12/I12>=1,"Fast Moving","Slow Moving")) -> Fast Moving | Z12: =Q12-TODAY() -> 825 | AA12: =IF(Q12<TODAY(),"Expired", IF(Q12-TODAY()<=7,"Critical", IF(Q12-TODAY()<=30,"Expiring Soon","Safe"))) -> Safe | AB12: =IF(I12<J12,"Low Stock","Sufficient") -> Low Stock | AC12: =K12 * N12 -> 160 | AD12: =IF(AND(AA12="Critical",AB12="Low Stock"),"High Risk", IF(AA12="Expired","Loss", IF(AA12="Expiring Soon","Discount Soon", IF(AB12="Low Stock","Reorder Needed","Healthy")))) -> Reorder Needed
A13: =Raw_Data!A13 -> 42-220-9305 | B13: White Sugar | C13: =TRIM(PROPER(Raw_Data!B13)) -> White Sugar | D13: Grains & Pulses | E13: =TRIM(PROPER(Raw_Data!C13)) -> Grains & Pulses | F13: 56-092-7992 | G13: Zooxo | H13: =TRIM(PROPER(Raw_Data!E13)) -> Zooxo | I13: 91 | J13: 98 | K13: =MAX(0,(J13*2)-I13) -> 105 | L13: Sufficient Stock | M13: $2.00 | N13: =VALUE(SUBSTITUTE(Raw_Data!I13,"$","")) -> 2 | O13: 45584 | P13: 45608 | Q13: =Raw_Data!L13 -> 46610 | R13: =IF(Q13<TODAY(),"Expired", IF(Q13<=TODAY()+30,"High", IF(Q13<=TODAY()+90,"Medium","Low") ) ) -> Low | S13: 61932 Cascade Crossing | T13: 100 | U13: =I13 * N13 -> 182 | V13: Backordered | W13: =I13 * N13 -> 182 | X13: =T13 * N13 -> 200 | Y13: =IF(T13=0,"No Sales", IF(T13/I13>=1,"Fast Moving","Slow Moving")) -> Fast Moving | Z13: =Q13-TODAY() -> 581 | AA13: =IF(Q13<TODAY(),"Expired", IF(Q13-TODAY()<=7,"Critical", IF(Q13-TODAY()<=30,"Expiring Soon","Safe"))) -> Safe | AB13: =IF(I13<J13,"Low Stock","Sufficient") -> Low Stock | AC13: =K13 * N13 -> 210 | AD13: =IF(AND(AA13="Critical",AB13="Low Stock"),"High Risk", IF(AA13="Expired","Loss", IF(AA13="Expiring Soon","Discount Soon", IF(AB13="Low Stock","Reorder Needed","Healthy")))) -> Reorder Needed
... A201: =Raw_Data!A201 -> 97-710-2449 | B201: Rye Bread | C201: =TRIM(PROPER(Raw_Data!B201)) -> Rye Bread | D201: Bakery | E201: =TRIM(PROPER(Raw_Data!C201)) -> Bakery | F201: 39-676-9308 | G201: Tanoodle | H201: =TRIM(PROPER(Raw_Data!E201)) -> Tanoodle | I201: 28 | J201: 94 | K201: =MAX(0,(J201*2)-I201) -> 160 | L201: Sufficient Stock | M201: $2.80 | N201: =VALUE(SUBSTITUTE(Raw_Data!I201,"$","")) -> 2.8 | O201: 45435 | P201: 45680 | Q201: =Raw_Data!L201 -> 45679 | R201: =IF(Q201<TODAY(),"Expired", IF(Q201<=TODAY()+30,"High", IF(Q201<=TODAY()+90,"Medium","Low") ) ) -> Expired | S201: 0 Miller Pass | T201: 31 | U201: =I201 * N201 -> 78.4 | V201: Backordered | W201: =I201 * N201 -> 78.4 | X201: =T201 * N201 -> 86.8 | Y201: =IF(T201=0,"No Sales", IF(T201/I201>=1,"Fast Moving","Slow Moving")) -> Fast Moving | Z201: =Q201-TODAY() -> -350 | AA201: =IF(Q201<TODAY(),"Expired", IF(Q201-TODAY()<=7,"Critical", IF(Q201-TODAY()<=30,"Expiring Soon","Safe"))) -> Expired | AB201: =IF(I201<J201,"Low Stock","Sufficient") -> Low Stock | AC201: =K201 * N201 -> 448 | AD201: =IF(AND(AA201="Critical",AB201="Low Stock"),"High Risk", IF(AA201="Expired","Loss", IF(AA201="Expiring Soon","Discount Soon", IF(AB201="Low Stock","Reorder Needed","Healthy")))) -> Loss

Sheet Pivot_Analysis
A1: CATEGORY PERFORMANCE | E1: SUPPLIER RISK OVERVIEW | J1: SUPPLIER EXPIRY RISK | O1: SUPPLIER STOCK RISK
A2: Category | B2: Sum of Total_Inventory_Value | C2: Sum of Estimated_Sales_Revenue | E2: Suppliers (Top 10) | F2: Sum of Inventory_Value | G2: Count of Product_ID | H2: Sum of Reorder_Cost_Estimate | J2: Sum of Inventory_Value | K2: Expiry_Risk_Level | O2: Count of Product_ID | P2: Stock_Risk_Level | S2: Supplier Name | T2: Total Inventory Value | W2: Sum of Total_Inventory_Value | Z2: Row Labels | AA2: Sales Volume | AC2: Date | AD2: Sum of Table1[Total_Inventory_Value] | AE2: Sum of Table1[Sales_Volume]
A3: Bakery | B3: 2889.1 | C3: 3880.7 | E3: Browsecat | F3: 1488 | G3: 1 | H3: 3286 | J3: Suppliers (Top 10) | K3: Expired | L3: Expiring Soon | M3: Safe | O3: Suppliers (Top 10) | P3: Low Stock | Q3: Sufficient | S3: Vinder | T3: 5809.58 | W3: 70056.38 | Z3: Jan | AA3: 900 | AC3: Jan | AD3: 6880.75 | AE3: 900
A4: Beverages | B4: 18018.5 | C4: 15999.5 | E4: Feedmix | F4: 1431 | G4: 3 | H4: 5609 | J4: Browsecat | M4: 1488 | O4: Bluezoom | Q4: 2 | S4: Skipstorm | T4: 2475 | Z4: Feb | AA4: 587 | AC4: Feb | AD4: 3595.6 | AE4: 587
A5: Dairy | B5: 10165.4 | C5: 9041.1 | E5: Meedoo | F5: 1656 | G5: 1 | H5: 792 | J5: Feedmix | K5: 900 | L5: 90 | M5: 441 | O5: Brainverse | P5: 2 | Q5: 1 | S5: Pixonyx | T5: 2310 | W5: Expiry_Risk_Level | X5: (Multiple Items) | Z5: Mar | AA5: 1081 | AC5: Mar | AD5: 4937.75 | AE5: 1081
A6: Fruits & Vegetables | B6: 18098.83 | C6: 16685.9 | E6: Midel | F6: 1199 | G6: 3 | H6: 594 | J6: Meedoo | L6: 1656 | O6: Bubblemix | P6: 2 | S6: Yadel | T6: 1986.25 | Z6: Apr | AA6: 746 | AC6: Apr | AD6: 3318.8 | AE6: 746
A7: Grains & Pulses | B7: 6220.35 | C7: 6197.2 | E7: Pixonyx | F7: 2310 | G7: 1 | H7: 390 | J7: Midel | M7: 1199 | O7: Dazzlesphere | P7: 2 | S7: Meedoo | T7: 1656 | W7: Count of Product_ID | Z7: May | AA7: 1374 | AC7: May | AD7: 8157.5 | AE7: 1374
A8: Oils & Fats | B8: 4022.2 | C8: 4065.6 | E8: Realpoint | F8: 1337.6 | G8: 2 | H8: 63.2 | J8: Pixonyx | M8: 2310 | O8: Devshare | Q8: 2 | S8: Voomm | T8: 1620 | W8: 7 | Z8: Jun | AA8: 582 | AC8: Jun | AD8: 3824 | AE8: 582
A9: Seafood | B9: 10642 | C9: 10648 | E9: Skipstorm | F9: 2475 | G9: 1 | H9: 1875 | J9: Realpoint | M9: 1337.6 | O9: Eayo | P9: 1 | Q9: 1 | S9: Browsecat | T9: 1488 | Z9: Jul | AA9: 554 | AC9: Jul | AD9: 2190.9 | AE9: 554
A10: STOCK RISK & REORDER COST | E10: Vinder | F10: 5809.58 | G10: 3 | H10: 276 | J10: Skipstorm | M10: 2475 | O10: Eidel | P10: 2 | S10: Feedmix | T10: 1431 | W10: Sum of Table1[Reorder_Cost_Estimate] | Z10: Aug | AA10: 1697 | AC10: Aug | AD10: 9706.1 | AE10: 1697
A11: Stock Risk Level | B11: Count of Product_ID | C11: Sum of Reorder_Cost_Estimate | E11: Voomm | F11: 1620 | G11: 2 | H11: 2340 | J11: Vinder | K11: 117.5 | M11: 5692.08 | O11: Eire | P11: 1 | Q11: 1 | S11: Realpoint | T11: 1337.6 | W11: 20876.2 | Z11: Sep | AA11: 892 | AC11: Sep | AD11: 8494.58 | AE11: 892
A12: Low Stock | B12: 99 | C12: 63074.55 | E12: Yadel | F12: 1986.25 | G12: 2 | H12: 1731.25 | J12: Voomm | K12: 380 | M12: 1240 | O12: Feedbug | P12: 2 | S12: Midel | T12: 1199 | Z12: Oct | AA12: 1099 | AC12: Oct | AD12: 5529.7 | AE12: 1099
A13: Sufficient | B13: 101 | C13: 14350.15 | J13: Yadel | M13: 1986.25 | O13: Feedmix | P13: 3 | S13: Skivee | T13: 1100 | W13: Supplier Dependency % | Z13: Nov | AA13: 1039 | AC13: Nov | AD13: 8173.4 | AE13: 1039
A14: PRODUCT HEALTH SUMMARY | O14: Fiveclub | Q14: 2 | S14: Flipbug | T14: 1080.6 | W14: 0.082927208 | Z14: Dec | AA14: 741 | AC14: Dec | AD14: 5247.3 | AE14: 741
A15: Product Health | B15: Count of Product_ID | C15: Sum of Total_Inventory_Value | O15: Flipbug | Q15: 2 | S15: Realbridge | T15: 1044 | Z15: Grand Total | AA15: 11292 | AC15: Grand Total | AD15: 70056.38 | AE15: 11292
A16: Discount Soon | B16: 5 | C16: 2940.6 | O16: Gigaclub | Q16: 2 | S16: Skajo | T16: 990 | W16: Est. Sales Revenue
A17: Healthy | B17: 68 | C17: 34353.13 | O17: Gigazoom | P17: 2 | Q17: 1 | S17: Cogibox | T17: 937.5 | W17: 66518
A18: Loss | B18: 56 | C18: 14559.8 | O18: Jabbertype | P18: 1 | Q18: 1 | S18: Grand Total | T18: 26464.53
A19: Reorder Needed | B19: 71 | C19: 18202.85 | O19: Kamba | P19: 2 | W19: Row Labels | X19: Count of Product_ID
A20: EXPIRY RISK ANALYSIS | O20: Katz | Q20: 2 | W20: Critical | X20: 1
A21: Expiry Risk Level | B21: Sum of Inventory_Value | C21: Count of Product_ID | O21: Linklinks | Q21: 2 | W21: Expired | X21: 60
A22: Expired | B22: 14559.8 | C22: 56 | O22: Meevee | P22: 2 | W22: Expiring Soon | X22: 6
A23: Expiring Soon | B23: 2940.6 | C23: 5 | O23: Midel | Q23: 3 | W23: Safe | X23: 133
A24: Safe | B24: 52555.98 | C24: 139 | O24: Mydeo | P24: 1 | Q24: 2 | W24: Grand Total | X24: 200
A25: FAST vs SLOW MOVING PRODUCTS | O25: Mydo | P25: 2 | Q25: 1
A26: Turnover Status | B26: Sum of Estimated_Sales_Revenue | C26: Count of Product_ID | O26: Mynte | P26: 2
A27: Fast Moving | B27: 38026.8 | C27: 109 | O27: Reallinks | Q27: 2
A28: Slow Moving | B28: 28491.2 | C28: 91 | O28: Realpoint | Q28: 2
O29: Shufflester | Q29: 2 | S29: Row Labels | T29: Count of Table1[Product_ID]
O30: Skidoo | P30: 1 | Q30: 1 | S30: Active | T30: 67 | W30: Row Labels | X30: Inventory | Y30: Sales Efficiency by Category
O31: Skimia | Q31: 2 | S31: Backordered | T31: 51 | W31: Fruits & Vegetables | X31: 18098.83 | Y31: 16685.9
O32: Skipfire | P32: 1 | Q32: 1 | S32: Discontinued | T32: 82 | W32: Beverages | X32: 18018.5 | Y32: 15999.5
O33: Skyble | Q33: 2 | S33: Grand Total | T33: 200 | W33: Seafood | X33: 10642 | Y33: 10648
O34: Skynoodle | P34: 2 | W34: Dairy | X34: 10165.4 | Y34: 9041.1
O35: Tagtune | P35: 1 | Q35: 1 | W35: Grains & Pulses | X35: 6220.35 | Y35: 6197.2
O36: Tanoodle | P36: 2 | W36: Oils & Fats | X36: 4022.2 | Y36: 4065.6
O37: Thoughtblab | Q37: 2 | S37: Row Labels | T37: Count of Product_ID | W37: Bakery | X37: 2889.1 | Y37: 3880.7
O38: Thoughtstorm | P38: 1 | Q38: 1 | S38: Low Stock | T38: 99 | W38: Grand Total | X38: 70056.38 | Y38: 66518
O39: Topicstorm | P39: 1 | Q39: 2 | S39: Sufficient | T39: 101
O40: Vinder | P40: 1 | Q40: 2 | S40: Grand Total | T40: 200
O41: Voomm | P41: 1 | Q41: 1
O42: Yadel | Q42: 2
O43: Zooxo | P43: 2
S45: Row Labels | T45: Est Sales Rev
S46: Bakery | T46: 3880.7
S47: Beverages | T47: 15999.5
S48: Dairy | T48: 9041.1
S49: Fruits & Vegetables | T49: 16685.9
S50: Grains & Pulses | T50: 6197.2
S51: Oils & Fats | T51: 4065.6
S52: Seafood | T52: 10648
S53: Grand Total | T53: 66518
S58: Category | T58: Value of Inventory
S59: Bakery | T59: 2889.1
S60: Beverages | T60: 18018.5
S61: Dairy | T61: 10165.4
S62: Fruits & Vegetables | T62: 18098.83
S63: Grains & Pulses | T63: 6220.35
S64: Oils & Fats | T64: 4022.2
S65: Seafood | T65: 10642
S66: Grand Total | T66: 70056.38

Sheet KPI Pivots
A1: Inventory Health KPIs | F1: Sales & Profitability | K1: Inventory Efficiency & Supplier Risk
A3: Total SKUs | C3: Row Labels | D3: Active SKUs | F3: Sales Revenue | G3: Inventory Value | H3: Total Sales | I3: Product Count
A4: 200 | C4: Active | D4: 67 | F4: 66518 | G4: 70056.38 | H4: 11292 | I4: 200 | K4: Slow-Moving SKU Count | Q4: Single-Source Dependency % | R4: Single Supplier SKUs/Total SKUs | S4: =VALUE(3/200) -> 0.015
C5: Grand Total | D5: 67 | K5: Row Labels | L5: Product Count | Q5: Row Labels | R5: Revenue | S5: Count Products
F6: Total Profit = Sales Revenue - Inventory Value | G6: Profit Margin = Total Profit/Sales Revenue | H6: Revenue Per SKU | I6: Total Sales | K6: Fast Moving | L6: 109 | Q6: Vinder | R6: 3751.05 | S6: 3
A7: Stockout Risk Count | C7: Row Labels | D7: Non Active Inventory | F7: =VALUE(70056-66518) -> 3538 | G7: =VALUE(3538/66518) -> 0.053188611 | H7: =VALUE(66518/200) -> 332.59 | I7: 11292 | K7: Slow Moving | L7: 91 | Q7: Grand Total | R7: 3751.05 | S7: 3
A8: {=SUMPRODUCT(--(Clean_Data!I2:I201 < Clean_Data!J2:J201))} -> 99 | C8: Backordered | D8: 51 | K8: Grand Total | L8: 200
C9: Discontinued | D9: 82
C10: Grand Total | D10: 133
A11: Non Active Inventory % = | K11: Supplier Concentration Risk | M11: =VALUE(3751/11292) -> 0.33218208 | Q11: Average Inventory per SKU
A12: =VALUE(133/200) -> 0.665
K13: Row Labels | L13: Supplier Sales Revenue | M13: Count of Table1[Product_Name_Clean] | N13: Sum of Table1[Sales_Volume] | Q13: Avg Inventory Value Per Product | R13: Product Volume
K14: Vinder | L14: 3751.05 | M14: 3 | N14: 114 | Q14: 350.2819 | R14: 200
K15: Blogtag | L15: 1020 | M15: 1 | N15: 85
K16: Browsecat | L16: 2170 | M16: 1 | N16: 70
K17: Feedmix | L17: 2345 | M17: 3 | N17: 155
K18: Flipbug | L18: 1180.95 | M18: 2 | N18: 118
K19: Jaxspan | L19: 980 | M19: 1 | N19: 98
K20: Midel | L20: 1429 | M20: 3 | N20: 217
K21: Skipstorm | L21: 2325 | M21: 1 | N21: 93
K22: Yadel | L22: 1985.25 | M22: 2 | N22: 134
K23: Zazio | L23: 1068 | M23: 1 | N23: 89
K24: Grand Total | L24: 18254.25 | M24: 18 | N24: 1173

Sheet Dashboard
